setup.py
markphi/Binomialdistribution.py
markphi/Gaussiandistribution.py
markphi/Generaldistribution.py
markphi/__init__.py
markphi.egg-info/PKG-INFO
markphi.egg-info/SOURCES.txt
markphi.egg-info/dependency_links.txt
markphi.egg-info/not-zip-safe
markphi.egg-info/top_level.txt